gsheets3/__init__.py
gsheets3/admin.py
gsheets3/apps.py
gsheets3/decorators.py
gsheets3/gsheets.py
gsheets3/management/__init__.py
gsheets3/management/commands/__init__.py
gsheets3/management/commands/syncgsheets.py
gsheets3/migrations/__init__.py
gsheets3/mixins.py
gsheets3/models.py
gsheets3/settings.py
gsheets3/signals/__init__.py
gsheets3/tests.py
gsheets3/urls.py
gsheets3/views.py
gsheets3-0.1.3.dist-info/METADATA
gsheets3-0.1.3.dist-info/WHEEL
gsheets3-0.1.3.dist-info/RECORD
